rcrbounds.py
rcrbounds-3.0.1.dist-info/METADATA
rcrbounds-3.0.1.dist-info/WHEEL
rcrbounds-3.0.1.dist-info/top_level.txt
rcrbounds-3.0.1.dist-info/RECORD
