Metadata-Version: 2.4
Name: rcrbounds
Version: 3.0.1
Summary: RCR bounds (Krauth 2016)
Home-page: https://github.com/bvkrauth/rcr
Author: Brian Krauth
Author-email: bkrauth@sfu.ca
License: MIT
Requires-Dist: numpy
Requires-Dist: pandas
Requires-Dist: scipy
Requires-Dist: statsmodels
Requires-Dist: matplotlib
